odoo/addons/sale_commission_product_criteria_domain/README.rst
odoo/addons/sale_commission_product_criteria_domain/__init__.py
odoo/addons/sale_commission_product_criteria_domain/__manifest__.py
odoo/addons/sale_commission_product_criteria_domain/demo/demo_data.xml
odoo/addons/sale_commission_product_criteria_domain/i18n/es.po
odoo/addons/sale_commission_product_criteria_domain/i18n/it.po
odoo/addons/sale_commission_product_criteria_domain/i18n/sale_commission_product_criteria_domain.pot
odoo/addons/sale_commission_product_criteria_domain/models/__init__.py
odoo/addons/sale_commission_product_criteria_domain/models/account_invoice_line_agent.py
odoo/addons/sale_commission_product_criteria_domain/models/commission.py
odoo/addons/sale_commission_product_criteria_domain/models/commission_group.py
odoo/addons/sale_commission_product_criteria_domain/models/partner.py
odoo/addons/sale_commission_product_criteria_domain/models/sale_commission_line_mixin.py
odoo/addons/sale_commission_product_criteria_domain/models/sale_order_line_agent.py
odoo/addons/sale_commission_product_criteria_domain/readme/CONTRIBUTORS.rst
odoo/addons/sale_commission_product_criteria_domain/readme/DESCRIPTION.rst
odoo/addons/sale_commission_product_criteria_domain/readme/USAGE.rst
odoo/addons/sale_commission_product_criteria_domain/security/ir.model.access.csv
odoo/addons/sale_commission_product_criteria_domain/security/sale_commission_security.xml
odoo/addons/sale_commission_product_criteria_domain/static/description/icon.png
odoo/addons/sale_commission_product_criteria_domain/static/description/index.html
odoo/addons/sale_commission_product_criteria_domain/tests/__init__.py
odoo/addons/sale_commission_product_criteria_domain/tests/test_sale_commission_product_criteria_domain.py
odoo/addons/sale_commission_product_criteria_domain/views/views.xml
odoo14_addon_sale_commission_product_criteria_domain-14.0.1.0.12.dist-info/METADATA
odoo14_addon_sale_commission_product_criteria_domain-14.0.1.0.12.dist-info/WHEEL
odoo14_addon_sale_commission_product_criteria_domain-14.0.1.0.12.dist-info/top_level.txt
odoo14_addon_sale_commission_product_criteria_domain-14.0.1.0.12.dist-info/RECORD
